chess_export/__main__.py
chess_export/common.py
chess_export/py.typed
chess_export/chessdotcom/export.py
chess_export/chessdotcom/model.py
chess_export/lichess/export.py
chess_export/lichess/model.py
chess_export-0.1.1.dist-info/LICENSE
chess_export-0.1.1.dist-info/METADATA
chess_export-0.1.1.dist-info/WHEEL
chess_export-0.1.1.dist-info/entry_points.txt
chess_export-0.1.1.dist-info/top_level.txt
chess_export-0.1.1.dist-info/RECORD
