Metadata-Version: 2.1
Name: chess-export
Version: 0.1.1
Summary: Export your chess.com/lichess.org games
Home-page: https://github.com/seanbreckenridge/chess_export
Author: Sean Breckenridge
Author-email: seanbrecke@gmail.com
License: MIT
Keywords: chess data
Classifier: License :: OSI Approved :: MIT License
Classifier: Programming Language :: Python
Classifier: Programming Language :: Python :: 3
Classifier: Programming Language :: Python :: 3.8
Classifier: Programming Language :: Python :: 3.9
Classifier: Programming Language :: Python :: 3.10
Classifier: Programming Language :: Python :: 3.11
License-File: LICENSE
Requires-Dist: click (>=7.0)
Requires-Dist: requests
Requires-Dist: IPython
Provides-Extra: testing
Requires-Dist: mypy ; extra == 'testing'
